pyDataconverter/__init__.py
pyDataconverter/dataconverter.py
pyDataconverter/pipelinedADC.py
pyDataconverter/setup.py
pyDataconverter-0.2.dist-info/METADATA
pyDataconverter-0.2.dist-info/WHEEL
pyDataconverter-0.2.dist-info/top_level.txt
pyDataconverter-0.2.dist-info/RECORD
