Metadata-Version: 2.2
Name: pyDataconverter
Version: 0.2
Summary: A Python toolbox for modeling and analyzing data converters
Home-page: https://github.com/levantlabs/pyDataconverter
Author: Levant Labs
Classifier: Programming Language :: Python :: 3
Classifier: License :: OSI Approved :: GNU General Public License v3 (GPLv3)
Classifier: Operating System :: OS Independent
Classifier: Development Status :: 3 - Alpha
Classifier: Intended Audience :: Science/Research
Classifier: Topic :: Scientific/Engineering :: Electronic Design Automation (EDA)
Requires-Python: >=3.7
Requires-Dist: numpy
Requires-Dist: scipy
Requires-Dist: matplotlib
Dynamic: author
Dynamic: classifier
Dynamic: description
Dynamic: description-content-type
Dynamic: home-page
Dynamic: requires-dist
Dynamic: requires-python
Dynamic: summary
